smartcity/__init__.py
smartcity/__main__.py
smartcity/energy.py
smartcity/engine.py
smartcity/env.py
smartcity/factory.py
smartcity/people.py
smartcity/scores.py
smartcity/smart_city.py
smartcity/utils.py
smartcity/data/big.json
smartcity/data/medium.json
smartcity/data/small.json
src/__init__.py
src/__main__.py
src/energy.py
src/engine.py
src/env.py
src/factory.py
src/people.py
src/scores.py
src/smart_city.py
src/utils.py
src/happiness_criteria/__init__.py
src/happiness_criteria/eather.py
src/happiness_criteria/light.py
smartcity-1.0.0.dist-info/LICENCE
smartcity-1.0.0.dist-info/METADATA
smartcity-1.0.0.dist-info/WHEEL
smartcity-1.0.0.dist-info/top_level.txt
smartcity-1.0.0.dist-info/RECORD
