Metadata-Version: 2.1
Name: smartcity
Version: 1.0.0
Summary: A Smart City Env designed for Reinforcement Learning
Home-page: https://github.com/Ricocotam/SmartCity-simulator
Author: Adrien Pouyet (Ricocotam)
Author-email: ricocotam@gmail.Com
License: UNKNOWN
Platform: UNKNOWN
Classifier: Programming Language :: Python :: 3
Classifier: License :: OSI Approved :: MIT License
Classifier: Operating System :: OS Independent
Requires-Python: >=3.7
